{
    "name": "Sweater Weather",
    "creators": ["VelYT"],
    "verifier": "Domtacube",
    "verification": "https://www.youtube.com/watch?v=IiVXE9mvOQE",
    "percentToQualify": 100,
    "records": [
        {
            "user": "Zaki",
            "link": "https://www.youtube.com/watch?v=a1WTAnljLEY",
            "percent": 100
        },
        {
            "user": "SunnyAgus",
            "link": "https://youtu.be/uQgTWd_stSM?si=jLUQq0N7ReZN-eDl",
            "percent": 100
        }
    ]
}
